sedpy/__init__.py
sedpy/__main__.py
sedpy/sedpy.py
sedpy-1.0.0.dist-info/LICENSE.txt
sedpy-1.0.0.dist-info/METADATA
sedpy-1.0.0.dist-info/WHEEL
sedpy-1.0.0.dist-info/entry_points.txt
sedpy-1.0.0.dist-info/top_level.txt
sedpy-1.0.0.dist-info/RECORD
