Metadata-Version: 2.1
Name: sedpy
Version: 1.0.0
Summary: Cross-platform stream-line editing tool
Home-page: https://github.com/mritunjaysharma394/sedpy
Author: Mritunjay Sharma
Author-email: mritunjaysharma394@gmail.com
License: MIT
Platform: UNKNOWN
Classifier: License :: OSI Approved :: MIT License
Classifier: Programming Language :: Python :: 2.7
Classifier: Programming Language :: Python :: 3
Classifier: Programming Language :: Python :: 3.5
Classifier: Programming Language :: Python :: 3.6
Classifier: Programming Language :: Python :: 3.7
Classifier: Programming Language :: Python :: 3.8
